search_me_server/__init__.py
search_me_server/api.py
search_me_server-1.0.1.post0.dist-info/LICENSE
search_me_server-1.0.1.post0.dist-info/METADATA
search_me_server-1.0.1.post0.dist-info/WHEEL
search_me_server-1.0.1.post0.dist-info/top_level.txt
search_me_server-1.0.1.post0.dist-info/RECORD
