Metadata-Version: 2.1
Name: search-me-server
Version: 1.0.1.post0
Summary: Minimal server implementation for package search-me
Home-page: https://bit.ly/bitbucket-search-me-server
Author: Michael R. Kisel
Author-email: deploy-me@yandex.ru
License: MIT
Keywords: aiohttp search,aiohttp server,async downloader,async parser,async pdf parse,async pdf report,async scraper,async search,async search-me server,async search-me,async server,async social search,async,downloader,facebook,google,instagram,parser,pdf parse,pdf report,rambler,scraper,search,search-me server,search-me,searx,snapchat,social downloader,social search,socials,telegram,text summary,tumblr,twitter,vk,web downloader,web scraper,web search,web social search,youtube
Platform: UNKNOWN
Classifier: Development Status :: 5 - Production/Stable
Classifier: Environment :: Console
Classifier: Intended Audience :: Science/Research
Classifier: Intended Audience :: End Users/Desktop
Classifier: Intended Audience :: Developers
Classifier: License :: OSI Approved :: MIT License
Classifier: Operating System :: OS Independent
Classifier: Programming Language :: Python :: 3.7
Classifier: Programming Language :: Python :: 3.8
Classifier: Programming Language :: Python :: 3.9
Classifier: Topic :: Internet
Classifier: Topic :: Sociology
Classifier: Topic :: Software Development
Requires-Python: >=3.7.1
Requires-Dist: search-me
